{
    "raw": {
        "importedFiles": {
            "utility-types": [
                "names",
                [
                    [
                        "$Diff",
                        "$Diff"
                    ]
                ]
            ],
            "./TouchableWithoutFeedback": [
                "default",
                "TouchableWithoutFeedback$f2tTypeof"
            ],
            "../../../Libraries/Animated/Animated": [
                "default",
                "Animated"
            ],
            "../../../Libraries/StyleSheet/StyleSheet": [
                "names",
                [
                    [
                        "ViewStyleProp",
                        "ViewStyleProp"
                    ]
                ]
            ],
            "react": [
                "namespace",
                "React"
            ]
        },
        "exports": {},
        "exportDefault": [
            "symbol",
            "$f2tExportDefault"
        ]
    },
    "importedNames": {
        "$Diff": [
            "utility-types",
            "$Diff"
        ],
        "ViewStyleProp": [
            "../../../Libraries/StyleSheet/StyleSheet",
            "ViewStyleProp"
        ]
    },
    "importedNamespaces": {
        "React": "react"
    },
    "importedDefaults": {
        "TouchableWithoutFeedback$f2tTypeof": "./TouchableWithoutFeedback",
        "Animated": "../../../Libraries/Animated/Animated"
    },
    "decls": [
        [
            "TouchableWithoutFeedback",
            [
                "TSTypeAliasDeclaration"
            ]
        ],
        [
            "TVProps",
            [
                "TSTypeAliasDeclaration"
            ]
        ],
        [
            "Props",
            [
                "TSTypeAliasDeclaration"
            ]
        ],
        [
            "$f2tExportDefault",
            [
                "VariableDeclarator"
            ]
        ]
    ]
}