{
    "raw": {
        "importedFiles": {
            "../NativeExceptionsManager": [
                "names",
                [
                    [
                        "StackFrame",
                        "StackFrame"
                    ]
                ]
            ]
        },
        "exports": {
            "ExtendedError": [
                "rename",
                "ExtendedError"
            ]
        },
        "exportDefault": [
            "symbol",
            "$f2tExportDefault"
        ]
    },
    "importedNames": {
        "StackFrame": [
            "../NativeExceptionsManager",
            "StackFrame"
        ]
    },
    "importedNamespaces": {},
    "importedDefaults": {},
    "decls": [
        [
            "ExtendedError",
            "TSTypeAliasDeclaration"
        ],
        [
            "$f2tExportDefault",
            "VariableDeclarator"
        ]
    ]
}