{
    "raw": {
        "importedFiles": {
            "../EventEmitter/NativeEventEmitter": [
                "default",
                "NativeEventEmitter"
            ],
            "./XMLHttpRequest": [
                "names",
                [
                    [
                        "NativeResponseType",
                        "NativeResponseType"
                    ]
                ]
            ],
            "./convertRequestBody": [
                "names",
                [
                    [
                        "RequestBody",
                        "RequestBody"
                    ]
                ]
            ]
        },
        "exports": {},
        "exportDefault": [
            "symbol",
            "$f2tExportDefault"
        ]
    },
    "importedNames": {
        "NativeResponseType": [
            "./XMLHttpRequest",
            "NativeResponseType"
        ],
        "RequestBody": [
            "./convertRequestBody",
            "RequestBody"
        ]
    },
    "importedNamespaces": {},
    "importedDefaults": {
        "NativeEventEmitter": "../EventEmitter/NativeEventEmitter"
    },
    "decls": [
        [
            "RCTNetworking",
            [
                "ClassDeclaration"
            ]
        ],
        [
            "$f2tExportDefault",
            [
                "VariableDeclarator"
            ]
        ]
    ]
}