{
    "raw": {
        "importedFiles": {
            "./AnimatedInterpolation": [
                "names",
                [
                    [
                        "InterpolationConfigType",
                        "InterpolationConfigType"
                    ]
                ]
            ],
            "./AnimatedWithChildren": [
                "default",
                "$3"
            ],
            "../animations/Animation": [
                "default",
                "Animation"
            ],
            "./AnimatedTracking": [
                "default",
                "AnimatedTracking"
            ]
        },
        "exports": {},
        "exportDefault": [
            "symbol",
            "AnimatedValue"
        ]
    },
    "importedNames": {
        "EndCallback": [
            "../animations/Animation",
            "EndCallback"
        ],
        "InterpolationConfigType": [
            "./AnimatedInterpolation",
            "InterpolationConfigType"
        ]
    },
    "importedNamespaces": {},
    "importedDefaults": {
        "$1": "./AnimatedInterpolation",
        "$3": "./AnimatedWithChildren",
        "Animation": "../animations/Animation",
        "AnimatedTracking": "./AnimatedTracking"
    },
    "decls": [
        [
            "AnimatedValue",
            [
                "ClassDeclaration"
            ]
        ]
    ]
}